[
    {
        "key": "Left_elbow",
        "coord": [
            0.8383817672729492,
            0.363889217376709,
            -0.5592162609100342
        ],
        "angle": 178.29700983253022
    },
    {
        "key": "Right_elbow",
        "coord": [
            0.20315667986869812,
            0.3523140847682953,
            -0.11161021888256073
        ],
        "angle": 164.05242418879507
    },
    {
        "key": "Left_shoulder",
        "coord": [
            0.7975023984909058,
            0.23803329467773438,
            -0.8137180209159851
        ],
        "angle": 45.43365925328337
    },
    {
        "key": "Right_shoulder",
        "coord": [
            0.2744888365268707,
            0.2220185399055481,
            -0.5322701930999756
        ],
        "angle": 50.16266825643651
    }
]